campaign/__init__.py
campaign/abstracts.py
campaign/admin.py
campaign/apps.py
campaign/compat.py
campaign/conf.py
campaign/context.py
campaign/context_processors.py
campaign/fields.py
campaign/forms.py
campaign/models.py
campaign/urls.py
campaign/utils.py
campaign/views.py
campaign/backends/__init__.py
campaign/backends/base.py
campaign/backends/send_mail.py
campaign/migrations/0001_initial.py
campaign/migrations/0002_blacklistentry_reason.py
campaign/migrations/0003_delete_bounceentry.py
campaign/migrations/0004_newsletter_from_email.py
campaign/migrations/0005_auto_20160128_0634.py
campaign/migrations/0006_auto_20160128_0858.py
campaign/migrations/__init__.py
campaign/templates/admin/campaign/campaign/change_form.html
campaign/templates/admin/campaign/campaign/send_object.html
campaign/templates/campaign/base.html
campaign/templates/campaign/subscribe.html
campaign/templates/campaign/unsubscribe.html
fluentcms_campaign-0.9.4.dist-info/METADATA
fluentcms_campaign-0.9.4.dist-info/RECORD
fluentcms_campaign-0.9.4.dist-info/WHEEL
fluentcms_campaign-0.9.4.dist-info/top_level.txt
