Metadata-Version: 2.1
Name: fluentcms-campaign
Version: 0.9.4
Summary: A basic newsletter app for django-fluent-pages
Home-page: https://github.com/bashu/fluentcms-campaign
Author: Basil Shubin
Author-email: basil.shubin@gmail.com
License: BSD License
Download-URL: https://github.com/bashu/fluentcms-campaign/zipball/master
Platform: UNKNOWN
Classifier: Development Status :: 4 - Beta
Classifier: Environment :: Web Environment
Classifier: Framework :: Django
Classifier: Intended Audience :: Developers
Classifier: License :: OSI Approved :: BSD License
Classifier: Operating System :: OS Independent
Classifier: Programming Language :: Python
Classifier: Programming Language :: Python :: 2
Classifier: Programming Language :: Python :: 2.7
Classifier: Programming Language :: Python :: 3
Classifier: Programming Language :: Python :: 3.4
Classifier: Topic :: Internet :: WWW/HTTP
Classifier: Topic :: Internet :: WWW/HTTP :: Dynamic Content
Classifier: Topic :: Software Development :: Libraries :: Python Modules
Requires: Django (>=1.4)
Requires-Dist: django-fluent-contents (>=1.0)
Requires-Dist: fluentcms-emailtemplates (>0.2.5)
Requires-Dist: swapper
